MANIFEST.in
README.md
setup.py
magictrader/__init__.py
magictrader/candle.py
magictrader/chart.py
magictrader/command.py
magictrader/const.py
magictrader/event.py
magictrader/indicator.py
magictrader/inifile.py
magictrader/messenger.py
magictrader/model.py
magictrader/position.py
magictrader/terminal.py
magictrader/utils.py
magictrader.egg-info/PKG-INFO
magictrader.egg-info/SOURCES.txt
magictrader.egg-info/dependency_links.txt
magictrader.egg-info/entry_points.txt
magictrader.egg-info/requires.txt
magictrader.egg-info/top_level.txt
magictrader/config/logging.ini
magictrader/template/mt.ini
magictrader/template/mytrade.py