Metadata-Version: 2.1
Name: magictrader
Version: 0.1.3
Summary: MagicTrader makes it easy to do system trade on zaif-exchange.
Home-page: https://github.com/curio184/magictrader
Author: Yusuke Oya
Author-email: curio@antique-cafe.net
License: MIT
Keywords: zaif zaifapi zaif-exchange trade bot
Platform: UNKNOWN
Classifier: Development Status :: 4 - Beta
Classifier: Intended Audience :: Developers
Classifier: License :: OSI Approved :: MIT License
Classifier: Operating System :: OS Independent
Classifier: Programming Language :: Python
Classifier: Programming Language :: Python :: 3
Classifier: Programming Language :: Python :: 3.5
Classifier: Programming Language :: Python :: 3.6
Classifier: Programming Language :: Python :: 3.7
Provides-Extra: ta-lib
